GameSave/__init__.py
GameSave/_metadata.py
pyobjc_framework_gamesave-12.1.dist-info/METADATA
pyobjc_framework_gamesave-12.1.dist-info/WHEEL
pyobjc_framework_gamesave-12.1.dist-info/pyobjc-build-info.txt
pyobjc_framework_gamesave-12.1.dist-info/top_level.txt
pyobjc_framework_gamesave-12.1.dist-info/RECORD
