Metadata-Version: 2.4
Name: pyobjc-framework-GameSave
Version: 12.1
Summary: Wrappers for the framework GameSave on macOS
Home-page: https://github.com/ronaldoussoren/pyobjc
Author: Ronald Oussoren
Author-email: pyobjc-dev@lists.sourceforge.net
License: MIT
Keywords: PyObjC,GameSave
Platform: MacOS X (>=25.0)
Classifier: Development Status :: 5 - Production/Stable
Classifier: Environment :: Console
Classifier: Environment :: MacOS X :: Cocoa
Classifier: Intended Audience :: Developers
Classifier: Natural Language :: English
Classifier: Operating System :: MacOS :: MacOS X
Classifier: Programming Language :: Python
Classifier: Programming Language :: Python :: 3
Classifier: Programming Language :: Python :: 3 :: Only
Classifier: Programming Language :: Python :: 3.10
Classifier: Programming Language :: Python :: 3.11
Classifier: Programming Language :: Python :: 3.12
Classifier: Programming Language :: Python :: 3.13
Classifier: Programming Language :: Python :: 3.14
Classifier: Programming Language :: Python :: 3.15
Classifier: Programming Language :: Python :: Implementation :: CPython
Classifier: Programming Language :: Python :: Free Threading :: 3 - Stable
Classifier: Programming Language :: Objective C
Classifier: Topic :: Software Development :: Libraries :: Python Modules
Classifier: Topic :: Software Development :: User Interfaces
Requires-Python: >=3.10
Requires-Dist: pyobjc-core>=12.1
Requires-Dist: pyobjc-framework-Cocoa>=12.1
Dynamic: author
Dynamic: author-email
Dynamic: classifier
Dynamic: description
Dynamic: description-content-type
Dynamic: home-page
Dynamic: keywords
Dynamic: license
Dynamic: platform
Dynamic: requires-dist
Dynamic: requires-python
Dynamic: summary
